nose2_html_report/__init__.py
nose2_html_report/html_report.py
nose2_html_report/render.py
nose2_html_report/templates/report.html
nose2_html_report-0.6.0.dist-info/DESCRIPTION.rst
nose2_html_report-0.6.0.dist-info/METADATA
nose2_html_report-0.6.0.dist-info/RECORD
nose2_html_report-0.6.0.dist-info/WHEEL
nose2_html_report-0.6.0.dist-info/metadata.json
nose2_html_report-0.6.0.dist-info/top_level.txt
