Metadata-Version: 2.0
Name: nose2-html-report
Version: 0.6.0
Summary: Generate an HTML report for your unit tests
Home-page: https://github.com/mgrijalva/nose2-html-report
Author: Michael Grijalva
Author-email: michaelgrij@gmail.com
License: MIT
Keywords: nose2,testing,reporting
Platform: UNKNOWN
Classifier: Development Status :: 3 - Alpha
Classifier: Intended Audience :: Developers
Classifier: Topic :: Software Development :: Testing
Classifier: License :: OSI Approved :: MIT License
Classifier: Programming Language :: Python :: 2.7
Classifier: Programming Language :: Python :: 3.4
Requires-Dist: jinja2
